HFODetector/__init__.py
HFODetector/hil.py
HFODetector/mni.py
HFODetector/ste.py
HFODetector/utils.py
HFODetector-0.0.25.dist-info/LICENSE
HFODetector-0.0.25.dist-info/METADATA
HFODetector-0.0.25.dist-info/WHEEL
HFODetector-0.0.25.dist-info/top_level.txt
HFODetector-0.0.25.dist-info/RECORD
