Metadata-Version: 2.1
Name: HFODetector
Version: 0.0.25
Summary: Package for detecting HFOs
Home-page: https://github.com/roychowdhuryresearch/HFO_Detector
Author: Xin Chen, Hoyoung Chung
Author-email: xinchen98@g.ucla.edu, taylorchung@ucla.edu
License: TDG Attribution Non-Commercial No Distrib
Classifier: Intended Audience :: Science/Research
Classifier: Operating System :: OS Independent
Classifier: Programming Language :: Python :: 3.9
Requires-Python: >=3.6
License-File: LICENSE
Requires-Dist: mne
Requires-Dist: numpy
Requires-Dist: scipy
Requires-Dist: matplotlib
Requires-Dist: pandas
Requires-Dist: scikit-image
